op2_parser/__init__.py
op2_parser/__main__.py
op2_parser/exceptions.py
op2_parser/log.conf
op2_parser/op_parser.py
op2_parser/op_visitor.py
op2_parser/operation.peg
op_parser-0.1.1.dist-info/LICENSE
op_parser-0.1.1.dist-info/METADATA
op_parser-0.1.1.dist-info/WHEEL
op_parser-0.1.1.dist-info/entry_points.txt
op_parser-0.1.1.dist-info/top_level.txt
op_parser-0.1.1.dist-info/RECORD
